rewards_api/__init__.py
rewards_api/cli.py
rewards_api/cli_args.py
rewards_api/config.py
rewards_api/main.py
rewards_api/streamer.py
rewards_api/utils.py
rewards_api-0.1.4.dist-info/METADATA
rewards_api-0.1.4.dist-info/WHEEL
rewards_api-0.1.4.dist-info/entry_points.txt
rewards_api-0.1.4.dist-info/top_level.txt
rewards_api-0.1.4.dist-info/RECORD
