Metadata-Version: 2.1
Name: rewards-api
Version: 0.1.4
Summary: rewards api cli package for starting the local rewards server
Home-page: https://github.com/rewards-ai/rewards-api/tree/latest
Author: rewards.ai
Author-email: proanindyadeep@gmail.com
Classifier: Programming Language :: Python :: 3
Classifier: License :: OSI Approved :: MIT License
Classifier: Operating System :: OS Independent
Requires-Python: >=3.7
Requires-Dist: opencv-python
Requires-Dist: flask (==2.2.3)
Requires-Dist: flask-cors
Requires-Dist: boto3
Requires-Dist: Flask[async]
